herd/__init__.py
herd/main.py
tests/__init__.py
tests/setup.py
tests/test_browser_automation.py
tests/test_twitter.py
herd_web-0.1.1.dist-info/METADATA
herd_web-0.1.1.dist-info/WHEEL
herd_web-0.1.1.dist-info/top_level.txt
herd_web-0.1.1.dist-info/RECORD
