Metadata-Version: 2.2
Name: herd-web
Version: 0.1.1
Requires-Dist: aiohttp>=3.8.0
Requires-Dist: nats-py>=2.2.0
Requires-Dist: sseclient-py>=1.7.2
Requires-Dist: nkeys>=0.1.0
Requires-Dist: python-dateutil>=2.8.0
Requires-Dist: dataclasses>=0.6
Requires-Dist: asyncio>=3.4.3
Requires-Dist: typing>=3.7.4
Provides-Extra: test
Requires-Dist: pytest>=7.4.0; extra == "test"
Requires-Dist: pytest-asyncio>=0.21.0; extra == "test"
Requires-Dist: python-dotenv>=1.0.0; extra == "test"
Dynamic: provides-extra
Dynamic: requires-dist
